cell_annotator/__init__.py
cell_annotator/_constants.py
cell_annotator/_docs.py
cell_annotator/_logging.py
cell_annotator/_prompts.py
cell_annotator/_response_formats.py
cell_annotator/check.py
cell_annotator/utils.py
cell_annotator/model/_api_keys.py
cell_annotator/model/_providers.py
cell_annotator/model/base_annotator.py
cell_annotator/model/cell_annotator.py
cell_annotator/model/llm_interface.py
cell_annotator/model/obs_beautifier.py
cell_annotator/model/sample_annotator.py
cell_annotator-0.2.1.dist-info/METADATA
cell_annotator-0.2.1.dist-info/WHEEL
cell_annotator-0.2.1.dist-info/licenses/LICENSE
cell_annotator-0.2.1.dist-info/RECORD
