Metadata-Version: 2.4
Name: cell-annotator
Version: 0.2.1
Summary: Automated cell annotation from scRNA-seq data using LLMs
Project-URL: Documentation, https://cell-annotator.readthedocs.io/
Project-URL: Homepage, https://cell-annotator.readthedocs.io/
Project-URL: Source, https://github.com/quadbio/cell-annotator
Author: Marius Lange
Maintainer-email: Marius Lange <mlange@ethz.ch>
License: MIT License
License-File: LICENSE
Classifier: Programming Language :: Python :: 3 :: Only
Classifier: Programming Language :: Python :: 3.11
Classifier: Programming Language :: Python :: 3.12
Classifier: Programming Language :: Python :: 3.13
Requires-Python: >=3.11
Requires-Dist: docrep
Requires-Dist: packaging
Requires-Dist: pydantic>=2
Requires-Dist: python-dotenv
Requires-Dist: rich
Requires-Dist: scanpy>=1.11
Requires-Dist: session-info2
Provides-Extra: all-providers
Requires-Dist: anthropic>=0.59; extra == 'all-providers'
Requires-Dist: google-genai>=1.27; extra == 'all-providers'
Requires-Dist: openai>=1.90; extra == 'all-providers'
Provides-Extra: anthropic
Requires-Dist: anthropic>=0.59; extra == 'anthropic'
Provides-Extra: colors
Requires-Dist: colorspacious>=1.1; extra == 'colors'
Provides-Extra: dev
Requires-Dist: pre-commit; extra == 'dev'
Requires-Dist: twine>=4.0.2; extra == 'dev'
Provides-Extra: doc
Requires-Dist: docutils!=0.18.*,!=0.19.*,>=0.8; extra == 'doc'
Requires-Dist: ipykernel; extra == 'doc'
Requires-Dist: ipython; extra == 'doc'
Requires-Dist: myst-nb>=1.1; extra == 'doc'
Requires-Dist: pandas; extra == 'doc'
Requires-Dist: setuptools; extra == 'doc'
Requires-Dist: sphinx-autodoc-typehints; extra == 'doc'
Requires-Dist: sphinx-book-theme>=1; extra == 'doc'
Requires-Dist: sphinx-copybutton; extra == 'doc'
Requires-Dist: sphinx-tabs; extra == 'doc'
Requires-Dist: sphinx>=8.1; extra == 'doc'
Requires-Dist: sphinxcontrib-bibtex>=1; extra == 'doc'
Requires-Dist: sphinxext-opengraph; extra == 'doc'
Provides-Extra: gemini
Requires-Dist: google-genai>=1.27; extra == 'gemini'
Provides-Extra: gpu
Requires-Dist: rapids-singlecell>=0.12; extra == 'gpu'
Provides-Extra: openai
Requires-Dist: openai>=1.90; extra == 'openai'
Provides-Extra: test
Requires-Dist: anthropic>=0.59; extra == 'test'
Requires-Dist: colorspacious>=1.1; extra == 'test'
Requires-Dist: coverage>=7.10; extra == 'test'
Requires-Dist: flaky; extra == 'test'
Requires-Dist: google-genai>=1.27; extra == 'test'
Requires-Dist: openai>=1.90; extra == 'test'
Requires-Dist: pytest; extra == 'test'
Requires-Dist: pytest-cov; extra == 'test'
Provides-Extra: tutorials
Requires-Dist: squidpy>=1.6; extra == 'tutorials'
